{"423":[928,"Matias Emiliano","Paranyez","27398929","20-27398929-4","Mon, 10 Sep 1979 00:00:00 GMT","",1,null,null,1214,"Thu, 04 Feb 2021 00:00:00 GMT",null,"Subcomisario, Division Operaciones Comisaria Vecinal 11A, Policia de la Ciudad",928,"Segun ODI","72615"],"538":[807,"Roberto Alejandro","Morales","24553176","20-24553176-2","Wed, 19 Mar 1975 00:00:00 GMT","",1,null,null,1675,"Thu, 24 Feb 2022 00:00:00 GMT",null,"Comisario, Jefe Division Operaciones Comisaria Vecinal 11A, Policia de la Ciudad de Buenos Aires",807,"Segun ODI","72209"],"649":[1273,"Fernando Luis","Treccozzi",null,null,null,"",1,null,null,2227,"Sat, 02 Jul 2022 00:00:00 GMT",null,"Subcomisario, Division Operaciones Comisaria Vecinal 11A,  Policia de la Ciudad de Buenos Aires",1273,"ODI","72638"],"653":[1282,"Valeria Cristina","Buono",null,null,null,"",2,null,null,2308,"Fri, 19 Aug 2022 00:00:00 GMT",null,"Subcomisario, Division Operaciones Comisaria Vecinal 11A, Policia de la Ciudad de Buenos Aires",1282,"ODI","1039"],"Comisarios":[[538,"Roberto Alejandro","Morales","Comisario, Jefe Division Operaciones Comisaria Vecinal 11A, Policia de la Ciudad de Buenos Aires"]],"Subcomisarios":[[649,"Fernando Luis","Treccozzi","Subcomisario, Division Operaciones Comisaria Vecinal 11A,  Policia de la Ciudad de Buenos Aires"],[653,"Valeria Cristina","Buono","Subcomisario, Division Operaciones Comisaria Vecinal 11A, Policia de la Ciudad de Buenos Aires"],[423,"Matias Emiliano","Paranyez","Subcomisario, Division Operaciones Comisaria Vecinal 11A, Policia de la Ciudad"]]}
