{"376":[950,"Daniel Enrique","Ferreyra","23154296","20-23154296-6","Thu, 28 Dec 1972 00:00:00 GMT","",1,null,null,2057,"Sat, 01 May 2021 00:00:00 GMT",null,"Subomisario, Division Operaciones Comisaria Vecinal 12A, Policia de la Ciudad",950,"Segun ODI","73142"],"378":[947,"Rodrigo David","Tuset","26821486","20-26821486-1","Mon, 15 May 1978 00:00:00 GMT","",1,null,null,1250,"Thu, 04 Feb 2021 00:00:00 GMT",null,"Subcomisario, 2do Jefe Division Barrio 20 (SIOU), Policia de la Ciudad",947,"Segun ODI","455"],"397":[936,"Javier Gustavo","Rodriguez","27312752","20-27312752-7","Sat, 04 Aug 1979 00:00:00 GMT","",1,null,null,1234,"Thu, 04 Feb 2021 00:00:00 GMT",null,"Subcomisario, Division Operaciones Comisaria Vecinal 12A, Policia de la Ciudad",936,"Segun ODI","410"],"404":[1021,"Maria Mercedes","Rebaynera",null,null,null,"",2,null,null,1404,"Wed, 27 Jan 2021 00:00:00 GMT",null,"Comisario, Departamento Prevencion Social de las Toxicomanias (SII), Policia de la Ciudad",1021,"Segun ODI","399"],"407":[934,"Carlos","Scheiermann","17144390","20-17144390-4","Wed, 18 Nov 1964 00:00:00 GMT","",1,null,null,1626,"Thu, 24 Feb 2022 00:00:00 GMT",null,"Comisario, Division Operaciones Comisaria Vecinal 12A, Policia de la Ciudad de Buenos Aires",934,"Segun ODI","72286"],"Comisarios":[[404,"Maria Mercedes","Rebaynera","Comisario, Departamento Prevencion Social de las Toxicomanias (SII), Policia de la Ciudad"],[407,"Carlos","Scheiermann","Comisario, Division Operaciones Comisaria Vecinal 12A, Policia de la Ciudad de Buenos Aires"]],"Subcomisarios":[[378,"Rodrigo David","Tuset","Subcomisario, 2do Jefe Division Barrio 20 (SIOU), Policia de la Ciudad"],[397,"Javier Gustavo","Rodriguez","Subcomisario, Division Operaciones Comisaria Vecinal 12A, Policia de la Ciudad"]]}
