{"366":[824,"Hernan Roberto","Moreno","24622514","20-24622514-2","Sat, 05 Jul 1975 00:00:00 GMT","",1,null,null,2238,"Sat, 06 Aug 2022 00:00:00 GMT",null,"Comisario, Division Operaciones Comisaria Vecinal 7C, Policia de la Ciudad de Buenos Aires",824,"Segun ODI","72205"],"400":[844,"Jorge Eduardo","Berga","17746786","20-17746786-4","Tue, 03 Aug 1965 00:00:00 GMT","",1,null,null,1061,"Thu, 04 Feb 2021 00:00:00 GMT",null,"Subcomisario, Division Operaciones Comisaria Vecinal 7C, Policia de la Ciudad",844,"Segun ODI","644"],"405":[846,"Laura Lorena","Salda\u00f1o","25906949","2725906949-7","Mon, 23 May 1977 00:00:00 GMT","",2,null,null,1065,"Thu, 04 Feb 2021 00:00:00 GMT",null,"Subcomisario, 2do Jefe Division Operaciones Comisaria Vecinal 7C, Policia de la Ciudad",846,"Segun ODI","3168"],"413":[849,"Marcelo Nicolas","Palomo","32108961","20-32108961-6","Wed, 21 May 1986 00:00:00 GMT","",1,null,null,1071,"Thu, 04 Feb 2021 00:00:00 GMT",null,"Subcomisario, Division Operaciones Comisaria Vecinal 7C, Policia de la Ciudad",849,"Segun ODI","330"],"Comisarios":[[366,"Hernan Roberto","Moreno","Comisario, Division Operaciones Comisaria Vecinal 7C, Policia de la Ciudad de Buenos Aires"]],"Subcomisarios":[[400,"Jorge Eduardo","Berga","Subcomisario, Division Operaciones Comisaria Vecinal 7C, Policia de la Ciudad"],[405,"Laura Lorena","Salda\u00f1o","Subcomisario, 2do Jefe Division Operaciones Comisaria Vecinal 7C, Policia de la Ciudad"],[413,"Marcelo Nicolas","Palomo","Subcomisario, Division Operaciones Comisaria Vecinal 7C, Policia de la Ciudad"]]}
